aiotcvectordb/__init__.py
aiotcvectordb/exceptions.py
aiotcvectordb/client/__init__.py
aiotcvectordb/client/httpclient.py
aiotcvectordb/client/stub.py
aiotcvectordb/model/__init__.py
aiotcvectordb/model/ai_database.py
aiotcvectordb/model/collection.py
aiotcvectordb/model/collection_view.py
aiotcvectordb/model/database.py
aiotcvectordb/model/document_set.py
aiotcvectordb-0.1.1.dist-info/METADATA
aiotcvectordb-0.1.1.dist-info/WHEEL
aiotcvectordb-0.1.1.dist-info/licenses/LICENSE
aiotcvectordb-0.1.1.dist-info/RECORD
