Metadata-Version: 2.4
Name: aiotcvectordb
Version: 0.1.1
Summary: Tencent VectorDB Python Async SDK
Project-URL: Homepage, https://github.com/alviezhang/aiotcvectordb
Project-URL: Repository, https://github.com/alviezhang/aiotcvectordb
Project-URL: Issues, https://github.com/alviezhang/aiotcvectordb/issues
Author: Alvie Zhang
License: MIT License
License-File: LICENSE
Keywords: aiohttp,async,database,tencent,vector,vectordb
Classifier: Intended Audience :: Developers
Classifier: License :: OSI Approved :: MIT License
Classifier: Operating System :: OS Independent
Classifier: Programming Language :: Python :: 3
Classifier: Programming Language :: Python :: 3.9
Classifier: Programming Language :: Python :: 3.10
Classifier: Programming Language :: Python :: 3.11
Classifier: Programming Language :: Python :: 3.12
Classifier: Programming Language :: Python :: 3.13
Classifier: Topic :: Database
Requires-Python: >=3.9
Requires-Dist: aiohttp
Requires-Dist: numpy
Requires-Dist: tcvdb-text
Requires-Dist: tcvectordb
